{"\/":8096,"\/blog\/beaver-builder-post":3,"\/blog\/a-very-delicious-blog":8,"\/blog\/another-beaver-builder-post":5,"\/blog\/typi-non-habent-claritatem":17,"\/single-page2":8,"\/single-page":10,"\/contact":3323,"\/blog\/just-another-post":10,"\/blog\/duis-autem":1,"\/blog\/pumpkins-recipe":4,"\/blog\/lorem-ipsum-dolor-sit-amet":4,"\/blog\/eggs":1,"\/blog\/no-comments":1,"\/home":1456,"\/faq":40,"\/models":98,"\/profile":10,"\/politica-privacidad":468,"\/privacy":177,"\/preguntas":126,"\/links":1288,"\/links\/politica-privacidad":317,"\/legal":32,"\/legal\/politica-privacidad":30,"\/contacto":111,"\/masajistas-eroticas":69,"\/erotic-masseurs":9,"\/testing":1,"\/test":1,"\/masajistas-eroticas\/beaver-builder-post":24,"\/masajistas-eroticas\/a-very-delicious-blog":10,"\/masajistas-eroticas\/another-beaver-builder-post":3,"\/masajistas-eroticas\/duis-autem":1,"\/masajistas-eroticas\/just-another-post":7,"\/masajistas-eroticas\/chica-1":27,"\/masajistas-eroticas\/eggs":4,"\/masajistas-eroticas\/lorem-ipsum-dolor-sit-amet":2,"\/masajistas-eroticas\/no-comments":4,"\/masajistas-eroticas\/typi-non-habent-claritatem":3,"\/masajistas-eroticas\/pumpkins-recipe":1,"\/erotic-masseurs\/chica-2":12,"\/erotic-masseurs\/chica-1":38,"\/masajistas-eroticas\/britney-spears":154,"\/erotic-masseurs\/britney-spears":6,"\/masajistas-eroticas\/chica-6":1,"\/masajistas-eroticas\/chica-2":6,"\/masajistas-eroticas\/chica-5":27,"\/masajistas-eroticas\/chica-10":12}